setup.cfg
setup.py
physpy/__init__.py
physpy/_abs.py
physpy.egg-info/PKG-INFO
physpy.egg-info/SOURCES.txt
physpy.egg-info/dependency_links.txt
physpy.egg-info/requires.txt
physpy.egg-info/top_level.txt