Metadata-Version: 1.0
Name: physpy
Version: 0.1.1
Summary: A SymPy-based library for calculating the error percentage for measured values
Home-page: https://kolesnichenkods.github.io/PhysPy/
Author: Daniil Kolesnichenko
Author-email: d.s.kolesnichenko@ya.ru
License: MIT
Platform: UNKNOWN
